traktor_nowplaying/__init__.py
traktor_nowplaying/bottle.py
traktor_nowplaying/cli.py
traktor_nowplaying/core.py
traktor_nowplaying/ogg.py
traktor_nowplaying/options.py
traktor_nowplaying/version.py
traktor_nowplaying-0.3.5.dist-info/LICENSE
traktor_nowplaying-0.3.5.dist-info/METADATA
traktor_nowplaying-0.3.5.dist-info/WHEEL
traktor_nowplaying-0.3.5.dist-info/entry_points.txt
traktor_nowplaying-0.3.5.dist-info/top_level.txt
traktor_nowplaying-0.3.5.dist-info/zip-safe
traktor_nowplaying-0.3.5.dist-info/RECORD
