Metadata-Version: 2.1
Name: traktor-nowplaying
Version: 0.3.5
Summary: traktor_nowplaying uses Traktor's broadcast functionality to extract metadata about the currently playing song.
Home-page: https://github.com/radusuciu/traktor_nowplaying
Author: Radu Suciu
Author-email: radusuciu@gmail.com
License: MIT License
Platform: any
Classifier: Environment :: Console
Classifier: Topic :: Multimedia :: Sound/Audio
Classifier: Intended Audience :: End Users/Desktop
Classifier: Programming Language :: Python :: 3
Classifier: Development Status :: 4 - Beta
Classifier: Natural Language :: English
Classifier: Intended Audience :: Developers
Classifier: License :: OSI Approved :: MIT License
Classifier: Operating System :: OS Independent
Classifier: Topic :: Software Development :: Libraries :: Python Modules
Requires-Python: >=3.6.2
